sigstore/__init__.py
sigstore/__main__.py
sigstore/_cli.py
sigstore/_utils.py
sigstore/errors.py
sigstore/hashes.py
sigstore/models.py
sigstore/oidc.py
sigstore/py.typed
sigstore/sign.py
sigstore/_internal/__init__.py
sigstore/_internal/key_details.py
sigstore/_internal/merkle.py
sigstore/_internal/sct.py
sigstore/_internal/timestamp.py
sigstore/_internal/trust.py
sigstore/_internal/tuf.py
sigstore/_internal/fulcio/__init__.py
sigstore/_internal/fulcio/client.py
sigstore/_internal/oidc/__init__.py
sigstore/_internal/oidc/oauth.py
sigstore/_internal/rekor/__init__.py
sigstore/_internal/rekor/checkpoint.py
sigstore/_internal/rekor/client.py
sigstore/_internal/rekor/client_v2.py
sigstore/_store/__init__.py
sigstore/_store/https%3A%2F%2Ftuf-repo-cdn.sigstage.dev/root.json
sigstore/_store/https%3A%2F%2Ftuf-repo-cdn.sigstage.dev/signing_config.v0.2.json
sigstore/_store/https%3A%2F%2Ftuf-repo-cdn.sigstage.dev/trusted_root.json
sigstore/_store/https%3A%2F%2Ftuf-repo-cdn.sigstore.dev/root.json
sigstore/_store/https%3A%2F%2Ftuf-repo-cdn.sigstore.dev/signing_config.v0.2.json
sigstore/_store/https%3A%2F%2Ftuf-repo-cdn.sigstore.dev/trusted_root.json
sigstore/dsse/__init__.py
sigstore/dsse/_predicate.py
sigstore/verify/__init__.py
sigstore/verify/policy.py
sigstore/verify/verifier.py
sigstore-4.2.0.dist-info/entry_points.txt
sigstore-4.2.0.dist-info/licenses/LICENSE
sigstore-4.2.0.dist-info/WHEEL
sigstore-4.2.0.dist-info/METADATA
sigstore-4.2.0.dist-info/RECORD
