Metadata-Version: 2.4
Name: sigstore
Version: 4.2.0
Summary: A tool for signing Python package distributions
Author-email: Sigstore Authors <sigstore-dev@googlegroups.com>
Requires-Python: >=3.10
Classifier: License :: OSI Approved :: Apache Software License
Classifier: Programming Language :: Python :: 3 :: Only
Classifier: Programming Language :: Python :: 3
Classifier: Programming Language :: Python :: 3.10
Classifier: Programming Language :: Python :: 3.11
Classifier: Programming Language :: Python :: 3.12
Classifier: Programming Language :: Python :: 3.13
Classifier: Programming Language :: Python :: 3.14
Classifier: Development Status :: 5 - Production/Stable
Classifier: Intended Audience :: Developers
Classifier: Topic :: Security
Classifier: Topic :: Security :: Cryptography
License-File: LICENSE
Requires-Dist: cryptography >= 42, < 47
Requires-Dist: id >= 1.1.0
Requires-Dist: importlib_resources ~= 5.7; python_version < '3.11'
Requires-Dist: pyasn1 ~= 0.6
Requires-Dist: pydantic >= 2,< 3
Requires-Dist: pyjwt >= 2.1
Requires-Dist: pyOpenSSL >= 23.0.0
Requires-Dist: requests
Requires-Dist: rich >= 13,< 15
Requires-Dist: rfc8785 ~= 0.1.2
Requires-Dist: rfc3161-client >= 1.0.3,< 1.1.0
Requires-Dist: sigstore-models == 0.0.6
Requires-Dist: sigstore-rekor-types == 0.0.18
Requires-Dist: tuf ~= 6.0
Requires-Dist: platformdirs ~= 4.2
Requires-Dist: build ; extra == "dev"
Requires-Dist: bump >= 1.3.2 ; extra == "dev"
Requires-Dist: sigstore[doc, test, lint] ; extra == "dev"
Requires-Dist: mkdocs-material[imaging] ; extra == "doc"
Requires-Dist: mkdocstrings-python ; extra == "doc"
Requires-Dist: bandit ; extra == "lint"
Requires-Dist: mypy ~= 1.1 ; extra == "lint"
Requires-Dist: ruff < 0.14.15 ; extra == "lint"
Requires-Dist: types-requests ; extra == "lint"
Requires-Dist: types-pyOpenSSL ; extra == "lint"
Requires-Dist: pytest ; extra == "test"
Requires-Dist: pytest-cov ; extra == "test"
Requires-Dist: pretend ; extra == "test"
Requires-Dist: coverage[toml] ; extra == "test"
Project-URL: Documentation, https://sigstore.github.io/sigstore-python/
Project-URL: Homepage, https://pypi.org/project/sigstore/
Project-URL: Issues, https://github.com/sigstore/sigstore-python/issues
Project-URL: Source, https://github.com/sigstore/sigstore-python
Provides-Extra: dev
Provides-Extra: doc
Provides-Extra: lint
Provides-Extra: test
